achtung/__init__.py
achtung/_version.py
achtung/achtung.py
achtung/alarm.py
achtung/consumer.py
achtung/evaluator.py
achtung/evaluator2.py
achtung/util.py
tangods_achtung-0.15.0.dist-info/licenses/LICENSE.txt
tangods_achtung-0.15.0.dist-info/METADATA
tangods_achtung-0.15.0.dist-info/WHEEL
tangods_achtung-0.15.0.dist-info/entry_points.txt
tangods_achtung-0.15.0.dist-info/top_level.txt
tangods_achtung-0.15.0.dist-info/RECORD
