Metadata-Version: 2.4
Name: tangods-achtung
Version: 0.15.0
Summary: Achtung, a Tango device for managing alarms (Panic compatible)
Author-email: KITS Software <kits-sw@maxiv.lu.se>
License:                     GNU GENERAL PUBLIC LICENSE
Project-URL: Homepage, http://www.maxiv.lu.se
Project-URL: Source, https://gitlab.com/MaxIV/dev-maxiv-achtung
Requires-Python: >=3.9
License-File: LICENSE.txt
Requires-Dist: pytango
Requires-Dist: pyparsing
Requires-Dist: httpx
Provides-Extra: tests
Requires-Dist: pytest-forked; extra == "tests"
Requires-Dist: pytest-asyncio; extra == "tests"
Requires-Dist: pytest-mock; extra == "tests"
Requires-Dist: pytest-httpx; extra == "tests"
Requires-Dist: pytest-httpserver; extra == "tests"
Requires-Dist: pytango-db==0.4.0; extra == "tests"
Dynamic: license-file
